LICENSE.txt
MANIFEST.in
README.md
README.rst
setup.py
pyloupe/__init__.py
pyloupe/__version__.py
pyloupe/cl_utils.py
pyloupe/default_settings.yaml
pyloupe/setup.cfg
pyloupe/utKit.py
pyloupe.egg-info/PKG-INFO
pyloupe.egg-info/SOURCES.txt
pyloupe.egg-info/dependency_links.txt
pyloupe.egg-info/not-zip-safe
pyloupe.egg-info/requires.txt
pyloupe.egg-info/top_level.txt
pyloupe/commonutils/__init__.py
pyloupe/commonutils/getpackagepath.py
pyloupe/tests/__init__.py