Metadata-Version: 1.1
Name: pyloupe
Version: 0.1
Summary: A python package and command-line tools to Tools for taking a closer look at rocks, namely moving objects found in space 
Home-page: https://github.com/thespacedoctor/pyloupe
Author: David Young
Author-email: davidrobertyoung@gmail.com
License: MIT
Download-URL: https://github.com/thespacedoctor/pyloupe/archive/v0.1.zip
Keywords: asteroid, neo, solar-system
Platform: UNKNOWN
Classifier: Development Status :: 4 - Beta
Classifier: License :: OSI Approved :: MIT License
Classifier: Programming Language :: Python :: 2.7
Classifier: Topic :: Utilities
